crossref_citedby_driver/__init__.py
hirmeos_crossref_citedby_driver-0.1.2.dist-info/LICENSE
hirmeos_crossref_citedby_driver-0.1.2.dist-info/METADATA
hirmeos_crossref_citedby_driver-0.1.2.dist-info/WHEEL
hirmeos_crossref_citedby_driver-0.1.2.dist-info/top_level.txt
hirmeos_crossref_citedby_driver-0.1.2.dist-info/RECORD
