Metadata-Version: 2.1
Name: hirmeos-crossref-citedby-driver
Version: 0.1.2
Summary: Functions required by the crossref-citedby-driver
Author-email: Cristian Garcia <cristian.garcia@ubiquitypress.com>, Rowan Hatherley <rowan.hatherley@ubiquitypress.com>
Classifier: Programming Language :: Python :: 3
Classifier: License :: OSI Approved :: MIT License
Classifier: Operating System :: OS Independent
Requires-Python: >=3.10
License-File: LICENSE
Requires-Dist: beautifulsoup4 <5.0,>=4.8.0
Requires-Dist: lxml <5.0,>=4.8.0
Requires-Dist: requests <3.0,>=2.0
